<author lang="es">
	<documents>
		<document><![CDATA[Plantea Trump que a EU “sólo ingresen los que nos aman” https://t.co/aJQdzfVPKC #Noticias]]></document>
		<document><![CDATA[Supuestos marinos secuestran a 5 policías de Aquila https://t.co/SXpk7xM8LN #Noticias]]></document>
		<document><![CDATA[Resistencia en Mexicali contra el gasolinazo y privatización del agua (Video) https://t.co/1E26ezamYn #Noticias]]></document>
		<document><![CDATA[Aprueban congresos locales desaparecer juntas de conciliación y arbitraje (Foto) https://t.co/dD0EZFu9uQ #Noticias]]></document>
		<document><![CDATA[Llamada con Trump deja muy mal parado al gobierno de EPN: Dresser (Video) https://t.co/dFwo5UeIcO #Noticias]]></document>
		<document><![CDATA[Charles Dickens, un escritor inspirado por la pobreza https://t.co/wuzkKrKgZR #Noticias]]></document>
		<document><![CDATA[La opinión pública se fue a vivir a las redes sociales: Carlos Páez (Video) https://t.co/HUWsklSUfq #Noticias]]></document>
		<document><![CDATA[“La comida fue deliciosa… pero el propietario es mexicano. No volveremos” https://t.co/6cixlMEl10 #Noticias]]></document>
		<document><![CDATA[Por bajas ventas, retiran productos Ivanka Trump de boutique en EU https://t.co/3BOuKFJR3x #Noticias]]></document>
		<document><![CDATA[Dresser y Meyer analizan Constitución de 1917 y la de CDMX (Video) https://t.co/JB2ZBUmYmW #Noticias]]></document>
		<document><![CDATA[México ha vivido al margen de su Constitución; documento, caduco y manipulado: Meyer y Dresser  https://t.co/860KKckN0U #Noticias]]></document>
		<document><![CDATA[Ignacio Marván cuenta ‘Cómo hicieron la Constitución de 1917’ https://t.co/RhPY16NWVZ #Noticias]]></document>
		<document><![CDATA[En 2017, millones de niñas serán víctimas de mutilación genital: Unicef https://t.co/epH1qXmYtQ #Noticias]]></document>
		<document><![CDATA[Trump y la Corte de EU; ‘SNL’ y la llamada con EPN: reporte de Esquivel desde Washington (Video) https://t.co/c2MGOcpGnW #Noticias]]></document>
		<document><![CDATA[Sin festejos, Isabel II cumple 65 años en el trono (Foto) https://t.co/Dani6YGdXx #Noticias]]></document>
		<document><![CDATA[Nueva Constitución elimina fuero y permite revocación de mandato: Encinas (Video) https://t.co/JWz2IMUewm #Noticias]]></document>
		<document><![CDATA[Faltan leyes secundarias para la Constitución de la CDMX: Mauricio Tabe (Video) https://t.co/sMRPCGbIE6 #Noticias]]></document>
		<document><![CDATA[Renegociación del TLCAN no impactará a mercados, prevé BMV https://t.co/sch54jcKyG #Noticias]]></document>
		<document><![CDATA[En Constitución de CDMX, importante decir “lo que evitamos que pasara”: Camacho (Video) https://t.co/zM4W3dx4t1 #Noticias]]></document>
		<document><![CDATA[Virus y evolución (#Niñonautas con Kirén Miret) https://t.co/Spk2mvdiyx #Noticias]]></document>
		<document><![CDATA[“Políticamente, México no está viviendo un momento constituyente”: Pedro Salazar Ugarte (Video) https://t.co/PZ0TIObNlg #Noticias]]></document>
		<document><![CDATA[Protesta en campo de refugiados de Grecia se sale de control (Fotos) https://t.co/y05TzroPue #Noticias]]></document>
		<document><![CDATA[Así quedó publicada la Constitución de la CDMX (Documento) https://t.co/zWzjugCStM #Noticias]]></document>
		<document><![CDATA[Un insurgente en la Casa Blanca: “Dinero” con Enrique Galván Ochoa (Video) https://t.co/uom8iJBcZC #Noticias]]></document>
		<document><![CDATA[Merkel será candidata en Alemania; y en Francia, Le Pen inicia con gran popularidad https://t.co/ZYnJgdm8Sx #Noticias]]></document>
		<document><![CDATA[Patriotas y Gaga se llevan el SB51 (Video) https://t.co/TDUvYSrz4w #Noticias]]></document>
		<document><![CDATA[Japón: sacrifican 69 mil pollos por cepa de gripe aviar https://t.co/rwWyWQFOgC #Noticias]]></document>
		<document><![CDATA[Estados, empresas y ex funcionarios de inteligencia, contra veto migratorio de Trump https://t.co/Xqks0bX1jg #Noticias]]></document>
		<document><![CDATA[¿Qué destacan hoy los diarios internacionales? #Titulares 6/02 (Video) https://t.co/RDwD2IbFlO #Noticias]]></document>
		<document><![CDATA[¿Qué destacan hoy los diarios nacionales? #Titulares 6/02 (Video) https://t.co/UKv3sidjXV #Noticias]]></document>
		<document><![CDATA[Captan a “cuidador” golpeando perros en la Condesa (Video) https://t.co/8gPoZmISrs #Noticias]]></document>
		<document><![CDATA[Sacude sismo de 5.7 grados a Colombia (Videos) https://t.co/CEqBAt53XH #Noticias]]></document>
		<document><![CDATA[EU perderá competitividad si cesa importaciones de México: Stiglitz https://t.co/TVgVaz3oD7 #Noticias]]></document>
		<document><![CDATA[Columnas políticas 6/02: Trump confirma injerencismo y marcha en su contra https://t.co/lAGpU8mhzV #Noticias]]></document>
		<document><![CDATA[Empresas de seguridad de Arturo Bermúdez, ex jefe policiaco de Duarte, aún operan en la CDMX https://t.co/ChhJ8QDtfT #Noticias]]></document>
		<document><![CDATA[#AristeguiEnVivo 6 de febrero: Trump, Peña, la Constitución de la CDMX, Mesa Política y más https://t.co/NrJK0lWjP5 #Noticias]]></document>
		<document><![CDATA[Problemas legales con veto migratorio, en primeras planas del mundo https://t.co/Y7GFww4Xcc #Noticias]]></document>
		<document><![CDATA[#Titulares 6/02: Trump, Peña y el país a prueba https://t.co/THMmFu59U3 #Noticias]]></document>
		<document><![CDATA[De Mexicali hasta Cuernavaca, más protestas contra gasolinazo (Video) https://t.co/wNanarlxll #Noticias]]></document>
		<document><![CDATA[NFL: Entran Patriotas en el selecto grupo de los multicampeones del Super Bowl (Tabla) https://t.co/Z0Vm7HxI5e #Noticias]]></document>
		<document><![CDATA[NFL: Suma Tom Brady su cuarto nombramiento como MVP de un Super Bowl (Video) https://t.co/Y01SJKUxF2 #Noticias]]></document>
		<document><![CDATA[El asiento vacío en el Super Bowl (Foto y video) https://t.co/GSZ28x3p53 #Noticias]]></document>
		<document><![CDATA[Liga MX: Se aferran Xolos de Tijuana al liderato general (Tablas) https://t.co/NG5VeoF13w #Noticias]]></document>
		<document><![CDATA[NFL: Resurge Patriotas de las cenizas para conquistar el Super Bowl LI (Adelanto) https://t.co/vjFaL7isLS #Noticias]]></document>
		<document><![CDATA[Así fue el show de Lady Gaga, al medio tiempo del #SB51 (Galería) https://t.co/Nmucb8n7UW #Noticias]]></document>
		<document><![CDATA[NFL: Ofrece Lady Gaga un show de gran derroche tecnológico (Video) https://t.co/0hmXOnLLFG #Noticias]]></document>
		<document><![CDATA[Arquidiócesis tacha de “asesina” a la nueva Constitución de la CDMX https://t.co/ksEIfcGn5d #Noticias]]></document>
		<document><![CDATA[Liga MX: Evita Rodolfo Pizarro segundo tropiezo rojiblanco en el Estadio Chivas (Video) https://t.co/4PEOyejqvV #Noticias]]></document>
		<document><![CDATA[Peña, “muy dispuesto” a obtener ayuda estadounidense: Trump https://t.co/YHAqxpOX3n #Noticias]]></document>
		<document><![CDATA[Del Mazo, precandidato único del PRI en Edomex; Delfina hace precampaña con AMLO en Neza https://t.co/DuSQtqNWcV #Noticias]]></document>
		<document><![CDATA[Cárteles mexicanos y Estado Islámico, “elevado riesgo” para Texas: estudio https://t.co/3HePWFfoBV #Noticias]]></document>
		<document><![CDATA[Trump despotrica contra el poder judicial de EU https://t.co/EX6WD3d0ef #Noticias]]></document>
		<document><![CDATA[“Atacar a México es ofendernos a todos”: ex presidente de Chile https://t.co/NiSXPPEoJ0 #Noticias]]></document>
		<document><![CDATA[Y a 100 años de la Constitución… mexicanos la conocen poco (Video) https://t.co/KOBCfqQjNb #Noticias]]></document>
		<document><![CDATA[Estos son el billete y la moneda conmemorativa de la Constitución de 1917 (Video) https://t.co/puFB5zvKbn #Noticias]]></document>
		<document><![CDATA[“México: el colmo de la dependencia”, artículo de Carlos Herrera de la Fuente https://t.co/nvDMobAbsq #Noticias]]></document>
		<document><![CDATA[En Veracruz, “cerco informativo” que “atenta” contra veracruzanos: periodistas (Carta) https://t.co/vd97Hi4cKl #Noticias]]></document>
		<document><![CDATA[Presidente de la Corte llama a defender la soberanía nacional (Video) https://t.co/IiON1EeXd0 #Noticias]]></document>
		<document><![CDATA[Liga MX: Salen Tuzos con un punto del Olímpico Universitario (Video) https://t.co/yjjdSr9qc3 #Noticias]]></document>
		<document><![CDATA[#SinVotoNoHayDinero claman en redes; propuesta de Kumamoto, en manos de diputados (Video) https://t.co/XxupIFfZYi #Noticias]]></document>
		<document><![CDATA[Mexicanos se “inyectan” ánimo ante muro (Foto) https://t.co/wMyYRm73Yg #Noticias]]></document>
		<document><![CDATA[Trump le cuelga a Peña Nieto… en parodia de ‘SNL’ (Video) https://t.co/LnRQbsrsJJ #Noticias]]></document>
		<document><![CDATA[México, a prueba; “se han conjuntado desafíos del exterior con retos del interior”: EPN https://t.co/I7XVjL1uay #Noticias]]></document>
		<document><![CDATA[Comanda Carlos Vela reacción de la Real Sociedad ante Osasuna (Video) https://t.co/MTDSXeN6gm #Noticias]]></document>
		<document><![CDATA[Promulgada, la primera Constitución de la CDMX https://t.co/MWerOjq5H1 #Noticias]]></document>
		<document><![CDATA[Villarreal rescata un punto en el Ramón Sánchez Pizjuán https://t.co/Pd6XdHkKwz #Noticias]]></document>
		<document><![CDATA[Desea Papa Francisco que el Super Bowl LI sea un símbolo de paz y amistad (Video) https://t.co/GXkhpztImJ #Noticias]]></document>
		<document><![CDATA[Jesús Silva-Herzog Márquez escribe en ‘Lecturas de la Constitución’ #PrimerosCapítulos https://t.co/dAXiMFiWfc #Noticias]]></document>
		<document><![CDATA[Javier Garciadiego analiza la trascendencia de la Constitución de 1917 https://t.co/DGFrrcvuu1 #Noticias]]></document>
		<document><![CDATA[PSV Eindhoven mantiene presión sobre los punteros en la Eredivisie https://t.co/xkC3364hyO #Noticias]]></document>
		<document><![CDATA[Liga MX: Pumas va por su cuarta victoria de la campaña ante Pachuca en CU (Video) https://t.co/cybVbthGpx #Noticias]]></document>
		<document><![CDATA[Critica Krugman al “así llamado presidente” Trump, por descalificar a juez federal https://t.co/XEfvbUPCMZ #Noticias]]></document>
		<document><![CDATA[Narro convoca a derrotar el cáncer https://t.co/gOKWz8Dz6d #Noticias]]></document>
		<document><![CDATA[NFL: Llega la euforia del Super Bowl LI a la Estación Espacial Internacional (Video) https://t.co/3ja6w7KQbw #Noticias]]></document>
		<document><![CDATA[NFL: ¿Alcanzará a Halcones su ataque para vencer a Patriotas? https://t.co/mSpuJnjHEn #Noticias]]></document>
		<document><![CDATA[Vinculan a proceso a Arturo Bermúdez, ex secretario de Seguridad de Javier Duarte https://t.co/HfJtpAnxtK #Noticias]]></document>
		<document><![CDATA[NFL: Halcones presumen un ataque temible…y defensa de papel (Video) https://t.co/z66lsaG638 #Noticias]]></document>
		<document><![CDATA[Salen “Leones” rasurados del Camp Nou https://t.co/idJO0F5aZQ #Noticias]]></document>
		<document><![CDATA[Vincent Viola, candidato de Trump a la Secretaría del Ejército, retira su nominación https://t.co/uQwr2p3pPd #Noticias]]></document>
		<document><![CDATA[NFL: Posee Patriotas un equipo balanceado para ganar el Super Bowl (Video) https://t.co/pdLJYYTThW #Noticias]]></document>
		<document><![CDATA[La decapitación, portada de Der Spiegel (Foto) https://t.co/MleWmMC7UY #Noticias]]></document>
		<document><![CDATA[Lanzan en CDMX taxis exclusivos para mujeres por medio de aplicación (Video) https://t.co/DI77AIiMrj #Noticias]]></document>
		<document><![CDATA[Convocan a marcha ciudadana contra Trump (Foto) https://t.co/NRC2vqOx4u #Noticias]]></document>
		<document><![CDATA[Revés a Trump: Suspenden veto migratorio y revierten cancelación de visas https://t.co/nTUTLaeCYq #Noticias]]></document>
		<document><![CDATA[Hoy No Circula no reduce contaminación en CDMX: Universidad de Berkeley https://t.co/uWu2e6a4v7 #Noticias]]></document>
		<document><![CDATA[En protesta contra Trump, mexicana devuelve visa de EU en Sonora https://t.co/eth7am3ITJ #Noticias]]></document>
		<document><![CDATA[Se pone Julio César Chávez Junior en manos de Ignacio Beristáin https://t.co/rABWPVTCq7 #Noticias]]></document>
		<document><![CDATA[Satisfechos “Canelo” y “Junior” por pelear en Las Vegas el 6 de mayo https://t.co/ExtrUAHYYz #Noticias]]></document>
		<document><![CDATA[Videos de la semana: Las revelaciones de Dolia Estévez sobre la llamada EPN-Trump https://t.co/IldIMJD0di #Noticias]]></document>
		<document><![CDATA[Blog “FridaGuerrera”, un acercamiento a los feminicidios https://t.co/IstIdRkiiI #Noticias]]></document>
		<document><![CDATA[Juez federal bloquea veto migratorio de Trump a nivel nacional https://t.co/Uf4LwHcHNB #Noticias]]></document>
		<document><![CDATA[Muere bebé por Zika; advierte Salud que podrían presentarse más casos https://t.co/51vM0xkFmy #Noticias]]></document>
		<document><![CDATA[“Déjame ver cómo va el muro…” (Video) https://t.co/OI9lycMLsY #Noticias]]></document>
		<document><![CDATA[ONU y ONG condenan asesinato de ecologista en Chihuahua https://t.co/oLq2J5yYFB #Noticias]]></document>
		<document><![CDATA[Oaxaca: empresas eólicas incumplen con pago de derechos en Juchitán https://t.co/db8Sfy6aAW #Noticias]]></document>
		<document><![CDATA[Cultura para el puente: “¡Viva México!”, danza que conmemora la Constitución (Foto) https://t.co/ABBvTZAwxG #Noticias]]></document>
		<document><![CDATA[Latinoamérica debe responder con dignidad y sin violencia a Trump: Rigoberta Menchú https://t.co/qj3OR3WIVd #Noticias]]></document>
		<document><![CDATA[Viaje del hijo de Trump costó a casi 100,000 dólares a contribuyentes: WP https://t.co/IDVRSVg6wt #Noticias]]></document>
		<document><![CDATA[PGR localiza y destruye casi 8 millones de plantas de amapola y mariguana en Oaxaca https://t.co/jfmHHLxbcV #Noticias]]></document>
		<document><![CDATA[Defiende Córdova legalidad de reducción salarial a consejeros del INE https://t.co/awWIMR25qW #Noticias]]></document>
	</documents>
</author>